speckle_automate/__init__.py
speckle_automate/automation_context.py
speckle_automate/fixtures.py
speckle_automate/runner.py
speckle_automate/schema.py
speckleifc/__init__.py
speckleifc/__main__.py
speckleifc/ifc_geometry_processing.py
speckleifc/ifc_openshell_helpers.py
speckleifc/importer.py
speckleifc/main.py
speckleifc/property_extraction.py
speckleifc/converter/__init__.py
speckleifc/converter/data_object_converter.py
speckleifc/converter/geometry_converter.py
speckleifc/converter/project_converter.py
speckleifc/converter/spatial_element_converter.py
speckleifc/licenses/IfcOpenShell-GPL-3.0.txt
speckleifc/licenses/IfcOpenShell-LGPL-3.0.txt
speckleifc/licenses/README.md
speckleifc/proxy_managers/__init__.py
speckleifc/proxy_managers/instance_proxy_manager.py
speckleifc/proxy_managers/level_proxy_manager.py
speckleifc/proxy_managers/render_material_proxy_manager.py
specklepy/__init__.py
specklepy/api/__init__.py
specklepy/api/client.py
specklepy/api/credentials.py
specklepy/api/host_applications.py
specklepy/api/operations.py
specklepy/api/resource.py
specklepy/api/wrapper.py
specklepy/api/models/__init__.py
specklepy/api/resources/__init__.py
specklepy/api/resources/current/__init__.py
specklepy/api/resources/current/active_user_resource.py
specklepy/api/resources/current/file_import_resource.py
specklepy/api/resources/current/model_ingestion_resource.py
specklepy/api/resources/current/model_resource.py
specklepy/api/resources/current/other_user_resource.py
specklepy/api/resources/current/project_invite_resource.py
specklepy/api/resources/current/project_resource.py
specklepy/api/resources/current/server_resource.py
specklepy/api/resources/current/subscription_resource.py
specklepy/api/resources/current/version_resource.py
specklepy/api/resources/current/workspace_resource.py
specklepy/core/__init__.py
specklepy/core/api/__init__.py
specklepy/core/api/client.py
specklepy/core/api/connector_versions.py
specklepy/core/api/credentials.py
specklepy/core/api/enums.py
specklepy-3.2.4.dist-info/METADATA
specklepy-3.2.4.dist-info/WHEEL
specklepy-3.2.4.dist-info/licenses/LICENSE
specklepy-3.2.4.dist-info/RECORD
