Metadata-Version: 2.4
Name: specklepy
Version: 3.2.4
Summary: The Python SDK for Speckle
Project-URL: repository, https://github.com/specklesystems/specklepy
Project-URL: documentation, https://speckle.guide/dev/py-examples.html
Project-URL: homepage, https://speckle.systems/
Author-email: Speckle Systems <devops@speckle.systems>
License: Apache-2.0
License-File: LICENSE
Requires-Python: <4.0,>=3.10.0
Requires-Dist: appdirs>=1.4.4
Requires-Dist: attrs>=24.3.0
Requires-Dist: deprecated>=1.2.15
Requires-Dist: gql[requests,websockets]<4.0.0,>=3.5.0
Requires-Dist: httpx>=0.28.1
Requires-Dist: pydantic-settings>=2.7.1
Requires-Dist: pydantic>=2.10.5
Requires-Dist: ujson>=5.10.0
Provides-Extra: speckleifc
Requires-Dist: ifcopenshell>=0.8.3.post2; extra == 'speckleifc'
